procmondf/Eula.txt
procmondf/Procmon.exe
procmondf/Procmon64.exe
procmondf/Procmon64a.exe
procmondf/README.MD
procmondf/__init__.py
procmondf/procmon.chm
procmondf/requirements.txt
procmondf/thirdparty.json
procmondf-0.10.dist-info/LICENSE.rst
procmondf-0.10.dist-info/METADATA
procmondf-0.10.dist-info/WHEEL
procmondf-0.10.dist-info/top_level.txt
procmondf-0.10.dist-info/RECORD
