Metadata-Version: 2.1
Name: procmondf
Version: 0.10
Summary: provides a convenient and efficient solution for capturing and analyzing system activity logs using Procmon and converting them to the pandas compatible Parquet file format (2% of the original pml file size)
Home-page: https://github.com/hansalemaos/procmondf
Author: Johannes Fischer
Author-email: aulasparticularesdealemaosp@gmail.com
License: MIT
Keywords: microsoft,procmon,pandas,DataFrame
Classifier: Development Status :: 4 - Beta
Classifier: Programming Language :: Python :: 3 :: Only
Classifier: Programming Language :: Python :: 3.10
Classifier: Topic :: Software Development :: Libraries :: Python Modules
Classifier: Topic :: Utilities
License-File: LICENSE.rst
Requires-Dist: getfilenuitkapython
Requires-Dist: kthread-sleep
Requires-Dist: numpy
Requires-Dist: pandas
Requires-Dist: pyarrow
Requires-Dist: subprocess-alive
Requires-Dist: touchtouch
